libname/.DS_Store
libname/CM_betweeness.py
libname/CM_betweenness.py
libname/CM_closeness.py
libname/CM_eigenvector.py
libname/CM_katz.py
libname/__init__.py
CentMeasureAlgo-1.0.1.dist-info/METADATA
CentMeasureAlgo-1.0.1.dist-info/WHEEL
CentMeasureAlgo-1.0.1.dist-info/top_level.txt
CentMeasureAlgo-1.0.1.dist-info/RECORD
